{
  "type": "fx",
  "date": "2026-04-19",
  "seoTitle": "USD/JPYとマクロ経済の相互作用分析",
  "seoDescription": "USD/JPYの動きとマクロ経済要因、特に金利や地政学的リスクの影響を深掘りします。",
  "article": "## 1. 1分で読める結論\n今日の相場は、地政学的緊張の高まりがUSD/JPYの下落を引き起こした。特に、米国の経済政策に対する懸念が影響し、リスクオフの動きが見られる。これにより、BTCにも影響が及んでいる。\n\n## 2. 今日の主要ドライバー3つ\n1. **地政学的リスクの高まり → USD/JPYの下落**  \n    米国とイランの緊張が高まり、投資家はリスクを避ける動きが強まった。これにより、安全資産としての円が買われ、USD/JPYが下げた。\n2. **米国金利の不透明感 → 流動性の低下**  \n    金利の見通しに不透明感が残り、投資家は様子見の姿勢を強めている。これが流動性を低下させ、相場全体に影響を及ぼしている。\n3. **株式市場の不安定さ → リスクオフの進行**  \n    株価が下落し、リスクオフの動きが加速。この傾向は、USD/JPYにも影響を与え、売り圧力が強まっている。\n\n## 3. 市場構造の解釈\n現在の相場は、地政学的リスクが主導している。この影響は一時的ではなく、一定の継続性があると考える。機関投資家や短期トレーダーがリスクオフの動きを進めており、投資家心理が悪化している。特に、米国の外交政策に対する懸念が強まっているため、この流れはしばらく続く可能性がある。\n\n## 4. USD/JPY分析\n現状、USD/JPYは下落トレンドにある。短期的にはさらなる下押しが予想され、中期的には地政学的リスクの影響を受けつつ、金利動向が重要な要素となる。今回の動きは「継続型」であり、売り圧力が引き続き強くなる可能性が高い。\n\n## 5. BTCへの波及\nUSD/JPYの下落は、リスクオフの動きに連動してBTCにも影響を及ぼす可能性がある。特に、投資家が資金を逃避させる際、BTCが代替資産として注目されることが考えられる。\n\n## 6. 強気・弱気の分岐条件\n- **強気の維持条件**: 地政学的リスクが緩和され、米国の金利政策に対する信頼が回復すること。\n- **弱気の変化条件**: 新たな地政学的緊張が発生し、米国経済指標が悪化する場合。\n\n## 7. 今日の示唆\n現在の相場では、地政学的リスクや米国の金利動向に注意を払うべき。また、今後の経済指標発表や政治的イベントが相場に与える影響を注視することが重要。特に、投資家心理がどのように変化するかが鍵となる。\n\n## 8. 今日の結論\n本日は地政学的リスクが相場の主要因となり、USD/JPYは下落傾向にある。この動きはしばらく続くと考えられ、投資家は慎重な姿勢を保つべきである。",
  "meta": {
    "sources": [
      "FXStreet",
      "Investing"
    ],
    "categories": [
      "fx_analysis",
      "macro",
      "fx"
    ],
    "newsCount": 15,
    "basicsLinks": [
      {
        "title": "FXとは？",
        "url": "../basics/fx/what-is-fx.html"
      },
      {
        "title": "なぜ為替は動くのか",
        "url": "../basics/fx/what-moves-fx.html"
      },
      {
        "title": "ドル円とは？USD/JPYの見方",
        "url": "../basics/fx/what-is-usdjpy.html"
      }
    ]
  },
  "news": [
    {
      "source": "FXStreet",
      "category": "fx_analysis",
      "market": "global",
      "lang": "en",
      "title": "Bitcoin vs Gold: The 396-day bullish signal just fired again",
      "link": "https://www.fxstreet.com/analysis/bitcoin-vs-gold-the-396-day-bullish-signal-just-fired-again-202604181104",
      "pubDate": "Sat, 18 Apr 2026 11:04:30 Z"
    },
    {
      "source": "Investing",
      "category": "macro",
      "market": "global",
      "lang": "en",
      "title": "The Laffer Curve in Action as High Tax Rates Trigger Brain Drain",
      "link": "https://www.investing.com/analysis/the-laffer-curve-in-action-as-high-tax-rates-trigger-brain-drain-200678715",
      "pubDate": "Apr 18, 2026 07:06 GMT"
    },
    {
      "source": "Investing",
      "category": "macro",
      "market": "global",
      "lang": "en",
      "title": "BLS Jobs Report Is Broken: Is There a Better Measure?",
      "link": "https://www.investing.com/analysis/bls-jobs-report-is-broken-is-there-a-better-measure-200678671",
      "pubDate": "Apr 18, 2026 07:05 GMT"
    },
    {
      "source": "Investing",
      "category": "macro",
      "market": "global",
      "lang": "en",
      "title": "How to Trade the Initial Balance Like a Pro",
      "link": "https://www.investing.com/analysis/how-to-trade-the-initial-balance-like-a-pro-200678607",
      "pubDate": "Apr 18, 2026 07:03 GMT"
    },
    {
      "source": "FXStreet",
      "category": "fx",
      "market": "global",
      "lang": "en",
      "title": "USD/CHF Price Forecast: Breaks below key SMAs, eyes on 0.7800",
      "link": "https://www.fxstreet.com/news/usd-chf-price-forecast-breaks-below-key-smas-eyes-on-07800-202604172230",
      "pubDate": "Fri, 17 Apr 2026 22:30:52 Z"
    },
    {
      "source": "FXStreet",
      "category": "fx",
      "market": "global",
      "lang": "en",
      "title": "US President Trump says he can trust Iranians – ABC News",
      "link": "https://www.fxstreet.com/news/us-president-trump-says-he-can-trust-iranians-abc-news-202604172208",
      "pubDate": "Fri, 17 Apr 2026 22:08:39 Z"
    },
    {
      "source": "Investing",
      "category": "macro",
      "market": "global",
      "lang": "en",
      "title": "US Economy Faces Whiplash as Supply Shocks Distort Jobs and Inflation",
      "link": "https://www.investing.com/analysis/us-economy-faces-whiplash-as-supply-shocks-distort-jobs-and-inflation-200678716",
      "pubDate": "Apr 17, 2026 21:38 GMT"
    },
    {
      "source": "FXStreet",
      "category": "fx",
      "market": "global",
      "lang": "en",
      "title": "Singapore: CPI seen higher on energy shock – DBS",
      "link": "https://www.fxstreet.com/news/singapore-cpi-seen-higher-on-energy-shock-dbs-202604172129",
      "pubDate": "Fri, 17 Apr 2026 21:29:00 Z"
    },
    {
      "source": "Investing",
      "category": "macro",
      "market": "global",
      "lang": "en",
      "title": "The War’s Economic Fallout Is Only Beginning",
      "link": "https://www.investing.com/analysis/crisis-in-transit-wars-economic-fallout-is-only-beginning-200678679",
      "pubDate": "Apr 17, 2026 21:05 GMT"
    },
    {
      "source": "FXStreet",
      "category": "fx",
      "market": "global",
      "lang": "en",
      "title": "AI: Competitive edge debate – UBS",
      "link": "https://www.fxstreet.com/news/ai-competitive-edge-debate-ubs-202604172038",
      "pubDate": "Fri, 17 Apr 2026 20:38:00 Z"
    },
    {
      "source": "FXStreet",
      "category": "fx",
      "market": "global",
      "lang": "en",
      "title": "Silver Price Forecast: Bullish and poised to close above $81",
      "link": "https://www.fxstreet.com/news/silver-price-forecast-bullish-and-poised-to-end-above-81-202604171957",
      "pubDate": "Fri, 17 Apr 2026 19:57:10 Z"
    },
    {
      "source": "FXStreet",
      "category": "fx",
      "market": "global",
      "lang": "en",
      "title": "China: Policy easing expectations trimmed – DBS",
      "link": "https://www.fxstreet.com/news/china-policy-easing-expectations-trimmed-dbs-202604171951",
      "pubDate": "Fri, 17 Apr 2026 19:51:00 Z"
    },
    {
      "source": "Investing",
      "category": "macro",
      "market": "global",
      "lang": "en",
      "title": "From ’Loads of Money’ to No Cash to Splash",
      "link": "https://www.investing.com/analysis/from-loads-of-money-to-no-cash-to-splash-200678711",
      "pubDate": "Apr 17, 2026 19:22 GMT"
    },
    {
      "source": "FXStreet",
      "category": "fx",
      "market": "global",
      "lang": "en",
      "title": "Gold surges past $4,850 as Hormuz reopening crushes the US Dollar",
      "link": "https://www.fxstreet.com/news/gold-surges-past-4-850-as-hormuz-reopening-crushes-the-us-dollar-202604171909",
      "pubDate": "Fri, 17 Apr 2026 19:09:58 Z"
    },
    {
      "source": "FXStreet",
      "category": "fx",
      "market": "global",
      "lang": "en",
      "title": "Asia FX: De-escalation hopes support regional currencies – MUFG",
      "link": "https://www.fxstreet.com/news/asia-fx-de-escalation-hopes-support-regional-currencies-mufg-202604171908",
      "pubDate": "Fri, 17 Apr 2026 19:08:00 Z"
    }
  ]
}